gluettalax.py
gluettalax-1.1.2.dist-info/LICENSE
gluettalax-1.1.2.dist-info/METADATA
gluettalax-1.1.2.dist-info/WHEEL
gluettalax-1.1.2.dist-info/entry_points.txt
gluettalax-1.1.2.dist-info/top_level.txt
gluettalax-1.1.2.dist-info/zip-safe
gluettalax-1.1.2.dist-info/RECORD
