Metadata-Version: 2.1
Name: gluettalax
Version: 1.1.2
Summary: Glue ETL without constipation
Home-page: https://github.com/andreax79/GLUEttalax
Author: Andrea Bonomi
Author-email: andrea.bonomi@gmail.com
License: MIT
Keywords: aws glue cli
Classifier: Intended Audience :: Developers
Classifier: Topic :: Utilities
Classifier: License :: Public Domain
Classifier: Natural Language :: English
Classifier: Operating System :: OS Independent
Classifier: Programming Language :: Python :: 3.6
Classifier: Programming Language :: Python :: 3.7
Classifier: Programming Language :: Python :: 3.8
Classifier: Programming Language :: Python :: 3.9
Classifier: Programming Language :: Python :: 3.10
License-File: LICENSE
Requires-Dist: boto3
